scopium/__init__.py
scopium/browsers.py
scopium/exceptions.py
scopium/launcher.py
scopium-1.0.0a0.dist-info/LICENSE
scopium-1.0.0a0.dist-info/METADATA
scopium-1.0.0a0.dist-info/WHEEL
scopium-1.0.0a0.dist-info/top_level.txt
scopium-1.0.0a0.dist-info/RECORD
