Metadata-Version: 2.1
Name: scopium
Version: 1.0.0a0
Home-page: https://github.com/khxql/Scopium
Author: Khaled Mahmoud Al Jamous
Classifier: Programming Language :: Python :: 3.8
Classifier: License :: OSI Approved :: MIT License
Classifier: Operating System :: Microsoft :: Windows :: Windows 10
Classifier: Operating System :: Microsoft :: Windows :: Windows 11
Classifier: Development Status :: 3 - Alpha
License-File: LICENSE
Requires-Dist: selenium
Requires-Dist: webdriver-manager
